README.md
setup.py
rasterpy/__init__.py
rasterpy/raster.py
rasterpy.egg-info/PKG-INFO
rasterpy.egg-info/SOURCES.txt
rasterpy.egg-info/dependency_links.txt
rasterpy.egg-info/requires.txt
rasterpy.egg-info/top_level.txt