Metadata-Version: 1.2
Name: rasterpy
Version: 0.0.1
Summary: Read and write geospatial raster datasets
Home-page: https://github.com/ibaris/rasterpy
Author: Ismail Baris
Maintainer: Ismail Baris
License: UNKNOWN
Keywords: radar,remote-sensing,optics,raster,gis,data,reader,write
Platform: UNKNOWN
Classifier: Intended Audience :: Science/Research
Classifier: Topic :: Scientific/Engineering :: Atmospheric Science
Classifier: License :: OSI Approved :: MIT License
Classifier: Programming Language :: Python :: 2.7
Classifier: Operating System :: Microsoft
